elasticsearch_async/__init__.py
elasticsearch_async/connection.py
elasticsearch_async/connection_pool.py
elasticsearch_async/helpers.py
elasticsearch_async/transport.py
elasticsearch_async-6.2.0.dist-info/METADATA
elasticsearch_async-6.2.0.dist-info/RECORD
elasticsearch_async-6.2.0.dist-info/WHEEL
elasticsearch_async-6.2.0.dist-info/top_level.txt
