Metadata-Version: 2.1
Name: elasticsearch-async
Version: 6.2.0
Summary: Async backend for elasticsearch-py
Home-page: https://github.com/elastic/elasticsearch-py-async
Author: Honza Král
Author-email: honza.kral@gmail.com
License: Apache License, Version 2.0
Platform: UNKNOWN
Classifier: Development Status :: 4 - Beta
Classifier: License :: OSI Approved :: Apache Software License
Classifier: Intended Audience :: Developers
Classifier: Operating System :: OS Independent
Classifier: Programming Language :: Python
Classifier: Programming Language :: Python :: 3 :: Only
Classifier: Programming Language :: Python :: 3.4
Classifier: Programming Language :: Python :: 3.5
Classifier: Programming Language :: Python :: 3.6
Classifier: Programming Language :: Python :: Implementation :: CPython
Requires-Python: ~=3.4
Provides-Extra: develop
Requires-Dist: aiohttp
Requires-Dist: async-timeout
Requires-Dist: elasticsearch (>=6.0.0)
Provides-Extra: develop
Requires-Dist: pytest; extra == 'develop'
Requires-Dist: pytest-asyncio; extra == 'develop'
Requires-Dist: pytest-cov; extra == 'develop'
